bfcm/__init__.py
bfcm/bfcm.py
bfcm/correlation_functions.py
bfcm/correlation_matrix.py
bfcm/fc_means.py
bfcm-0.1.1.dist-info/License.txt
bfcm-0.1.1.dist-info/METADATA
bfcm-0.1.1.dist-info/WHEEL
bfcm-0.1.1.dist-info/top_level.txt
bfcm-0.1.1.dist-info/RECORD
