Metadata-Version: 2.1
Name: bfcm
Version: 0.1.1
Summary: A library that quantifies implicit bias in tabular data with Fuzzy Cognitive Maps
Author: Isel Grau, Gonzalo Nápoles, Leonardo Concepción, Fabian Hoitsma, Lisa Koutsoviti, João Paulo Papa, Koen Vanhoof
Author-email: lisa.koutsoviti@uhasselt.be
License: MIT
License-File: License.txt
